L1I-Cache.v
`timescale 1ns / 1ps
`define DEBUG



/*/////////L1 instruction cache/////////////
//////Addressing a cache:
To retrieve a piece of data from a cache, an address must be provided to the cache in order for a search 
and hit/miss resolution to be made. The addres is broken down into three components (described below) of
which is required to fulfill three operations required to correctly search a cache. These are described below.

The cache has a 3 cycle latency.

////Offset:
The offset is composed of the addresses least significant bits and is used to indicate where within a cacheline 
the accessing data is found therefore this value only needs to be able to count as high at to the end of the cacheline.
EG: to access the eighth byte on a cacheline, the offset should be set to seven given zeroeth indexing.
Offset size = log_base2(#Uniquely addressable entries in a cacheline)
EG: 64 byte wide cache has 6 bits when each byte may be addressed uniquely.
NOTE: Power has fixed size 4 byte instructions therefore there are only 16 uniquely addressable entries
(isntructions) that we really need to read therefore the 2 lsbs of the address may be ommited with the values being
implicitley zeroed out therefore providing a 4 byte aligned offset for a 64 byte cacheline using only 4 bits.

////Index:
The index is used to locate which cacheline the requested data is found within. This starts on the bit just above the 
offset and is sized to cover the range of cachelines in the cache.
EG to access the fith cacheline, the index should be set to four.
Index size = log_base2(#cachelines)
EG a cache with 256 cachelines will have an index 8 bits wide.

////Tag:
The tag composes of all bits above the index up to the msb of the address, this is used to resolve cache hit/misses.
As many addresses share the same index and offsets, the tag indicates what cache-sized block of memory the index and
offset is associated with. This is stored in the tag memory and compared against the incoming address's tag. If they 
match then the cache is hit, otherwise it's a miss.

Writen by Josh "Hakaru" Cantwell - 16.12.2022
//////////////////////////////////////////*/
module L1I_Cache
#(
    parameter fetchingAddressWidth = 64, //addresses are 64 bits wide
    parameter cacheLineWith = 64 * 8, //cachelines are 64 bytes wide
    parameter instructionWidth = 4 * 8, // POWER instructions are 4 byte fixed sized
    parameter offsetWidth = 6, //allows all 16 instructions in the cache to be addresses (for a 64 byte wide cache)
    parameter indexWidth = 8, //256 cachelines
    parameter tagWidth = fetchingAddressWidth - (indexWidth - offsetWidth), //the tag is composed of the remaining parts of the address
    //Processes ID and thread ID size
    parameter PidSize = 20, parameter TidSize = 16, //1048K processes uniquly identifiable and 64K threads per process.
    parameter instructionCounterWidth = 80// 80 bit counter to uniquly identify instructions, this is known as the major ID as instructions may be broken into micro instructions which will have the same major ID yet unique minor IDs
)
(
    //////Inputs:
    input wire clock_i,
    ////Fetch:
    //command
    input wire fetchEnable_i, cacheReset_i, fetchStall_i,
    //data
    input wire [0:PidSize-1] Pid_i,
    input wire [0:TidSize-1] Tid_i,
    input wire [0:offsetWidth-1] offset_i,
    input wire [0:indexWidth-1] index_i,
    input wire [0:tagWidth-1] tag_i,

    /////Cache update:
    //command
    input wire cacheUpdate_i,
    //data
    input wire [0:fetchingAddressWidth-1] cacheUpdateAddress_i,
    input wire [0:PidSize-1] cacheUpdatePid_i,
    input wire [0:TidSize-1] cacheUpdateTid_i,
    input wire [0:cacheLineWith-1] cacheUpdateLine_i,


    //////Outputs:    
    ////Fetch:
    //command
    output reg fetchEnable_o,
    //data
    output reg [0:instructionWidth-1] fetchedInstruction_o,
    output reg [0:fetchingAddressWidth-1] fetchedAddress_o,
    //output wire [0:offsetWidth-1] fetchedOffset_o,
    //output wire [0:indexWidth-1] fetchedIndex_o,
    //output wire [0:tagWidth-1] fetchedTag_o,
    output reg [0:PidSize-1] fetchedPid_o,
    output reg [0:TidSize-1] fetchedTid_o,
    output reg [0:instructionCounterWidth-1] fetchedInstMajorId_o,

    ////Cache update:
    //command
    output reg cacheMiss_o,
    //data
    output reg [0:fetchingAddressWidth-1] missedAddress_o,
    output reg [0:instructionCounterWidth-1] missedInstMajorId_o,
    output reg [0:PidSize-1] missedPid_o,
    output reg [0:TidSize-1] missedTid_o
);

//loop counter
integer i;
//The actual cache memory
///Cacheline at idx i is at memory block tagTable[i] and is part of process processIdTable[i] and thread threadIdTable[i]
reg [0:cacheLineWith-1] ICache [0:indexWidth-1];//Stores the instructions
reg [0:tagWidth-1] tagTable [0:indexWidth-1];//Stores the tag for the associated cacheline
reg tagIsValidTable [0:indexWidth-1]; //indicates if the value is valid or not for the associated cacheline
reg [0:PidSize-1] processIdTable [0:indexWidth-1];//Stores the Pid for the associated cacheline
reg [0:TidSize-1] threadIdTable [0:indexWidth-1];//Stores the Tid for the associated cacheline
reg [0:instructionCounterWidth-1] instCtr;//uniquly identify instructions

reg [0:indexWidth-1] bufferIndex;
reg isValid;

//check the tag
reg [0:tagWidth-1] checkTag;


/////Cycle 1 memory input buffers - these buffers are required to allow the synth tool to instantiate the memories out using block RAM.
//Block memories need the inputs an output buffering
reg [0:indexWidth-1] fetchIndex_1;
/////Cycle 1 cypass buffers - these go alongside the memory input buffers to keep timing.
reg fetchEnable_1;
reg [0:offsetWidth-1] fetchOffset_1;
reg [0:tagWidth-1] fetchTag_1;
reg [0:PidSize-1] fetchPid_1;
reg [0:TidSize-1] fetchTid_1;
reg [0:instructionCounterWidth-1] instID_1;


/////Cycle 2 memory output buffers - these buffers are also required to allow the synth tool to instantiate the memories using block RAM. This means memory reads take 2 cycles.
//Block memory output buffers
reg [0:cacheLineWith-1] readLine_2;//holds the cacheline of the fetched instruction, if we can tell the instruction is on the same cacheline as last time we don't need to refetch the line from I-cache therefore saving power.
reg readLineIsValid_2;//indicates that the buffer is valid, will be inited to invalid
reg tagIsValid_2;//Indicates that the entry in the cache is valid, might be uninited or invalidated
reg [0:tagWidth-1] readTag_2;
/////Cycle 2 bypass buffers
reg fetchEnable_2;
reg [0:offsetWidth-1] fetchOffset_2;
reg [0:indexWidth-1] fetchIndex_2;
reg [0:tagWidth-1] fetchTag_2;
reg [0:PidSize-1] fetchPid_2;
reg [0:TidSize-1] fetchTid_2;
reg [0:instructionCounterWidth-1] instID_2;
/////cycle 3 hit/miss buffers
///On hit, output the inst
///on miss, make the request


////TODO:
//implement cache update
//implement instruction output

always @(posedge clock_i)
begin
    //Fetch
    fetchEnable_1 <= fetchEnable_i;//update the enable bypass buffer

    if(cacheReset_i)
    begin
    `ifdef DEBUG $display("Resetting cache"); `endif   
    instCtr <= 0;   
    readLineIsValid_2 <= 0;
    fetchEnable_1 <= 0;
    fetchEnable_2 <= 0;
    cacheMiss_o <= 0;
    for(i = 0; i < 256; i = i + 1)
    begin
        ICache[i] <= 0;
        tagTable[i] <= 0;
        tagIsValidTable[i] <= 0;
        processIdTable[i] <= 0;
        threadIdTable[i] <= 0;
    end

    end

    else if(fetchEnable_i && !cacheMiss_o)
    begin
    `ifdef DEBUG $display("Fetching instruction ID:%d at address %d.", instCtr, {tag_i, index_i, offset_i}); `endif
         //This cache assumes a hit and therefore begins fetching from the Icache, it later checks for a hit/miss
         //and takes the apropriate action. This allows the tag and the ICache to be interogated in parallel saving cycles.

        ///Cycle 1 - buffer the inputs for the memories and also the bypass buffers
        fetchIndex_1 <= index_i;//input to memories
        fetchOffset_1 <= offset_i;//bypass
        fetchTag_1 <= tag_i;//bypass
        fetchPid_1 <= Pid_i;//bapass
        fetchTid_1 <= Tid_i;//bypass
        //set unique inst ID and incr the ctr
        instID_1 <= instCtr;
        instCtr <= instCtr + 1;
    end
    else if(cacheMiss_o)   
    `ifdef DEBUG $display("Cycle 1 stalling due to cache miss"); `endif

    ///Cycle 2 - read from the memories into output bufferes using the input buffers and transfer the cycle1 bypass buffers to cycle2 bypass buffers
    //Check the fetchedLine buffer to see if the instruction exists on the line of the previous fetch, if so perform the fetch.
    if(fetchEnable_1 && !cacheMiss_o) 
    begin
        if( readLineIsValid_2 && //buffer is valid
            fetchTag_2 == fetchTag_1 && //on the same block of memory
            fetchIndex_2 == fetchIndex_1) //same cacheline
        begin
            //Fetch from the buffers as we're still on the same cacheline
            //so we'll do nothing here
            `ifdef DEBUG $display("Instruction on previously fetched line. Not refetching"); `endif
        end
        else
        begin
            `ifdef DEBUG $display("Instruction on new line. Refetching line."); `endif
            //Update the buffers and then fetch from the buffers
            readLine_2 <= ICache[fetchIndex_1]; 
            readLineIsValid_2 <= 1;
            readTag_2 <= tagTable[fetchIndex_1];
            tagIsValid_2 <= tagIsValidTable[fetchIndex_1];
            fetchPid_2 <= processIdTable[fetchIndex_1]; fetchTid_2 <= threadIdTable[fetchIndex_1];
            fetchTag_2 <= fetchTag_1; fetchIndex_2 <= fetchIndex_1;            
        end 
    end  
    else if(cacheMiss_o)   
    `ifdef DEBUG $display("Cycle 2 stalling due to cache miss"); `endif

    fetchOffset_2 <= fetchOffset_1;
    fetchEnable_2 <= fetchEnable_1;
    instID_2 <= instID_1;

    ///Cycle 3 - check for cache hit or miss
    if(fetchEnable_2&& !cacheMiss_o) begin
        if(fetchTag_2 == readTag_2 && tagIsValid_2)//hit
        begin
            `ifdef DEBUG $display("Cache hit."); `endif
            fetchEnable_o <= 1;
            fetchedInstruction_o <= readLine_2[(fetchOffset_2*8)+:32];
            fetchedAddress_o <= {fetchTag_2, fetchIndex_2, fetchOffset_2};
            fetchedPid_o <= fetchPid_2; fetchedTid_o <= fetchTid_2;
            fetchedInstMajorId_o <= instID_2;
        end
        else//miss
        begin
            `ifdef DEBUG $display("Cache miss."); `endif
            fetchEnable_o <= 0;
            cacheMiss_o <= 1; missedAddress_o <= {fetchTag_2, fetchIndex_2, fetchOffset_2};
            missedInstMajorId_o <= instID_2;
            missedPid_o <= fetchPid_2; missedTid_o <= fetchTid_2;
        end 
    end
    else if(cacheMiss_o)   
    `ifdef DEBUG $display("Cycle 3 stalling due to cache miss"); `endif

    ///Cache update/miss clear
    if(cacheUpdate_i)
    begin
        if(cacheMiss_o)//if we're currently stalled from a cache miss
        begin
            if(missedAddress_o[0+:tagWidth+indexWidth] == cacheUpdateAddress_i[0+:tagWidth+indexWidth] && //if were writing the cacheline that had caused the miss (Not checking the offset)
            cacheUpdatePid_i == missedPid_o && cacheUpdateTid_i == missedTid_o//and the process/thread is the same as the one causing the cache miss
            )
            begin
                cacheMiss_o <= 0; //clear the cache miss
                `ifdef DEBUG $display("Resolving cache miss as addr %d", cacheUpdateAddress_i); `endif
            end
            //NOTE: cacheUpdateAddress_i[tagWidth+:indexWidth] == index
            ICache[cacheUpdateAddress_i[tagWidth+:indexWidth]] <= cacheUpdateLine_i;//write the new line into the cache
            tagTable[cacheUpdateAddress_i[tagWidth+:indexWidth]] <= cacheUpdateAddress_i[0+:tagWidth];
            tagIsValidTable[cacheUpdateAddress_i[tagWidth+:indexWidth]] <= 1;
            processIdTable[cacheUpdateAddress_i[tagWidth+:indexWidth]] <= cacheUpdatePid_i;
            threadIdTable[cacheUpdateAddress_i[tagWidth+:indexWidth]] <= cacheUpdateTid_i;

            readLineIsValid_2 <= 0;
            fetchEnable_o <= 1;
            fetchedInstruction_o <= cacheUpdateLine_i[cacheUpdateAddress_i[tagWidth+indexWidth+:offsetWidth]+:32];
            fetchedAddress_o <= cacheUpdateAddress_i;
            fetchedPid_o <= cacheUpdatePid_i; fetchedTid_o <= cacheUpdateTid_i;
            fetchedInstMajorId_o <= missedInstMajorId_o;
        end
    end

end


endmodule

L1I-Cache_Test.v
`timescale 1ns / 1ps
`include "L1I-Cache.v"

module L1ICacheTest #(
    parameter fetchingAddressWidth = 64, //addresses are 64 bits wide
    parameter cacheLineWith = 64 * 8, //cachelines are 64 bytes wide
    parameter instructionWidth = 4 * 8, // POWER instructions are 4 byte fixed sized
    parameter offsetWidth = 6, //allows all 16 instructions in the cache to be addresses (for a 64 byte wide cache)
    parameter indexWidth = 8, //256 cachelines
    parameter tagWidth = fetchingAddressWidth - indexWidth - offsetWidth, //the tag is composed of the remaining parts of the address
    //Processes ID and thread ID size
    parameter PidSize = 20, parameter TidSize = 16, //1048K processes uniquly identifiable and 64K threads per process.
    parameter instructionCounterWidth = 80// 80 bit counter to uniquly identify instructions
)
(

);

//Fetch in
reg clockIn, fetchEnableIn, resetIn, fetchStallIn;
reg [0:PidSize-1] PidIn; reg [0:TidSize-1] TidIn;
reg [0:offsetWidth-1] OffsetIn; 
reg [0:indexWidth-1] IndexIn;
reg [0:tagWidth-1] TagIn;
//Update in
reg cacheUpdateIn;
reg [0:fetchingAddressWidth-1] updateAddressIn;
reg [0:cacheLineWith-1] cacheUpdateLineIn;
reg [0:PidSize-1] cacheUpdatePidIn;
reg [0:TidSize-1] cacheUpdateTidIn;
//Fetch out
wire enableOut;
wire [0:instructionWidth-1] fetchedInstructionOut;
wire [0:fetchingAddressWidth-1] fetchedAddressOut;
//wire [0:offsetWidth-1] fetchedOffset;
//wire [0:indexWidth-1] fetchedIndex;
//wire [0:tagWidth-1] fetchedTag;
wire [0:PidSize-1] fetchedPid;
wire [0:TidSize-1] fetchedTid;
wire [0:instructionCounterWidth-1] fetchedInstMajorId;
//Update out
wire cacheMissOut;
wire [0:fetchingAddressWidth-1] missedAddressOut;
wire [0:instructionCounterWidth-1] missedInstMajorId;
wire [0:PidSize-1] missedPidOut;
wire [0:TidSize-1] missedTidOut;

L1I_Cache #(
    .fetchingAddressWidth(fetchingAddressWidth), .cacheLineWith(cacheLineWith), 
    .instructionWidth(instructionWidth), .offsetWidth(offsetWidth), 
    .indexWidth(indexWidth), .tagWidth(tagWidth), 
    .PidSize(PidSize), .TidSize(TidSize), 
    .instructionCounterWidth(instructionCounterWidth)
)
l1ICache
(
    .clock_i(clockIn),
    //Fetch in 
    .fetchEnable_i(fetchEnableIn), .cacheReset_i(resetIn), .fetchStall_i(fetchStallIn), 
    .Pid_i(PidIn), .Tid_i(TidIn), .offset_i(OffsetIn), .index_i(IndexIn), .tag_i(TagIn), 
    //Update in
    .cacheUpdate_i(cacheUpdateIn), .cacheUpdateAddress_i(updateAddressIn), 
    .cacheUpdatePid_i(cacheUpdatePidIn), .cacheUpdateTid_i(cacheUpdateTidIn),
    .cacheUpdateLine_i(cacheUpdateLineIn),
    //Fetch out
    .fetchEnable_o(enableOut), .fetchedInstruction_o(fetchedInstructionOut), 

    .fetchedAddress_o(fetchedAddressOut),
    .fetchedPid_o(fetchedPid), .fetchedTid_o(fetchedTid), .fetchedInstMajorId_o(fetchedInstMajorId),
    //Update out
    .cacheMiss_o(cacheMissOut), .missedAddress_o(missedAddressOut),
    .missedInstMajorId_o(missedInstMajorId),
    .missedPid_o(missedPidOut), .missedTid_o(missedTidOut)
);

initial begin
    $dumpfile("FetchTest.vcd");
    $dumpvars(0,l1ICache);
    //init vars
    clockIn = 0; fetchEnableIn = 0;
    resetIn = 0; fetchStallIn = 0;
    PidIn = 0; TidIn = 0;
    OffsetIn = 0; IndexIn = 0;
    TagIn = 0;
    //update/resolve miss
    cacheUpdateIn = 0;
    updateAddressIn = 0; cacheUpdateLineIn = 0;
    cacheUpdatePidIn = 0; cacheUpdateTidIn = 0;
    #2;

    //reset
    resetIn = 1; clockIn = 1;
    #1;
    resetIn = 0; clockIn = 0;
    #1;

    //Start fetching
    clockIn = 1; fetchEnableIn = 1;
    TagIn = 0; IndexIn = 0; OffsetIn = 0;//Start fetching at addr 0
    #1;
    clockIn = 0; fetchEnableIn = 0;
    #1;

    //read from memories and check if inst already exists in buffer
    clockIn = 1;
    #1;
    clockIn = 0;
    #1;

    //Check for hit or miss
    clockIn = 1;
    #1;
    clockIn = 0;
    #1;

    //Start fetching again to test correct stall behaviour
    clockIn = 1; fetchEnableIn = 1;
    TagIn = 0; IndexIn = 0; OffsetIn = 4;//Start fetching at addr 0
    #1;
    clockIn = 0; fetchEnableIn = 0;
    #1;

    //read from memories and check if inst already exists in buffer
    clockIn = 1;
    #1;
    clockIn = 0;
    #1;

    //Check for hit or miss
    clockIn = 1;
    #1;
    clockIn = 0;
    #1;

    //clear the stall/miss
    cacheUpdateIn = 1;
    OffsetIn = 0;
    updateAddressIn = {TagIn, IndexIn, OffsetIn}; cacheUpdateLineIn = 102345;
    cacheUpdatePidIn = 0; cacheUpdateTidIn = 0;
    clockIn = 1;
    #1;
    cacheUpdateIn = 0;
    clockIn = 0;
    #1;

    //Start fetching again
    clockIn = 1; fetchEnableIn = 1;
    TagIn = 0; IndexIn = 0; OffsetIn = 4;//Start fetching at addr 0
    #1;
    clockIn = 0;
    #1;
    clockIn = 1;
    TagIn = 0; IndexIn = 0; OffsetIn = 8;//Start fetching at addr 0
    #1;
    clockIn = 0;
    #1;
    clockIn = 1;
    TagIn = 0; IndexIn = 0; OffsetIn = 12;//Start fetching at addr 0
    #1;
    clockIn = 0;
    #1;
    clockIn = 1;
    TagIn = 0; IndexIn = 0; OffsetIn = 16;//Start fetching at addr 0
    #1;
    clockIn = 0; fetchEnableIn = 0;
    #1;
    
    clockIn = 1;
    #1;
    clockIn = 0;
    #1;
    clockIn = 1;
    #1;
    clockIn = 0;
    #1;
end

endmodule

FetchTest.vcd
$date
	Sun Dec 18 21:02:59 2022
$end
$version
	Icarus Verilog
$end
$timescale
	1ps
$end
$scope module L1ICacheTest $end
$scope module l1ICache $end
$var wire 20 ! Pid_i [0:19] $end
$var wire 16 " Tid_i [0:15] $end
$var wire 1 # cacheReset_i $end
$var wire 64 $ cacheUpdateAddress_i [0:63] $end
$var wire 512 % cacheUpdateLine_i [0:511] $end
$var wire 20 & cacheUpdatePid_i [0:19] $end
$var wire 16 ' cacheUpdateTid_i [0:15] $end
$var wire 1 ( cacheUpdate_i $end
$var wire 1 ) clock_i $end
$var wire 1 * fetchEnable_i $end
$var wire 1 + fetchStall_i $end
$var wire 8 , index_i [0:7] $end
$var wire 6 - offset_i [0:5] $end
$var wire 50 . tag_i [0:49] $end
$var reg 1 / cacheMiss_o $end
$var reg 1 0 fetchEnable_1 $end
$var reg 1 1 fetchEnable_2 $end
$var reg 1 2 fetchEnable_o $end
$var reg 8 3 fetchIndex_1 [0:7] $end
$var reg 8 4 fetchIndex_2 [0:7] $end
$var reg 6 5 fetchOffset_1 [0:5] $end
$var reg 6 6 fetchOffset_2 [0:5] $end
$var reg 20 7 fetchPid_1 [0:19] $end
$var reg 20 8 fetchPid_2 [0:19] $end
$var reg 50 9 fetchTag_1 [0:49] $end
$var reg 50 : fetchTag_2 [0:49] $end
$var reg 16 ; fetchTid_1 [0:15] $end
$var reg 16 < fetchTid_2 [0:15] $end
$var reg 64 = fetchedAddress_o [0:63] $end
$var reg 80 > fetchedInstMajorId_o [0:79] $end
$var reg 32 ? fetchedInstruction_o [0:31] $end
$var reg 20 @ fetchedPid_o [0:19] $end
$var reg 16 A fetchedTid_o [0:15] $end
$var reg 80 B instCtr [0:79] $end
$var reg 80 C instID_1 [0:79] $end
$var reg 80 D instID_2 [0:79] $end
$var reg 64 E missedAddress_o [0:63] $end
$var reg 80 F missedInstMajorId_o [0:79] $end
$var reg 20 G missedPid_o [0:19] $end
$var reg 16 H missedTid_o [0:15] $end
$var reg 1 I readLineIsValid_2 $end
$var reg 512 J readLine_2 [0:511] $end
$var reg 50 K readTag_2 [0:49] $end
$var reg 1 L tagIsValid_2 $end
$var integer 32 M i [31:0] $end
$upscope $end
$upscope $end
$enddefinitions $end
#0
$dumpvars
bx M
xL
bx K
bx J
xI
bx H
bx G
bx F
bx E
bx D
bx C
bx B
bx A
bx @
bx ?
bx >
bx =
bx <
bx ;
bx :
bx 9
bx 8
bx 7
bx 6
bx 5
bx 4
bx 3
x2
x1
x0
x/
b0 .
b0 -
b0 ,
0+
0*
0)
0(
b0 '
b0 &
b0 %
b0 $
0#
b0 "
b0 !
$end
#2000
0/
x1
0I
b0 B
00
b100000000 M
1)
1#
#3000
0)
0#
#4000
01
b1 B
b0 C
b0 ;
b0 7
b0 9
b0 5
b0 3
10
1*
1)
#5000
0*
0)
#6000
b0 D
11
b0 6
b0 4
b0 :
b0 <
b0 8
0L
b0 K
1I
b0 J
00
1)
#7000
0)
#8000
b0 H
b0 G
b0 F
b0 E
1/
02
01
1)
#9000
0)
#10000
10
b100 -
1*
1)
#11000
0*
0)
#12000
11
00
1)
#13000
0)
#14000
01
1)
#15000
0)
#16000
b0 >
b0 A
b0 @
b0 =
b0 ?
12
0I
0/
1)
b11000111111001001 %
b0 -
1(
#17000
0)
0(
#18000
b10 B
b1 C
b100 5
10
b100 -
1*
1)
#19000
0)
#20000
b1 D
11
b100 6
1L
1I
b11000111111001001 J
b11 B
b10 C
b1000 5
b1000 -
1)
#21000
0)
#22000
b1 >
b100 =
b10 D
b1000 6
b100 B
b11 C
b1100 5
b1100 -
1)
#23000
0)
#24000
b10 >
b1000 =
b11 D
b1100 6
b101 B
b100 C
b10000 5
b10000 -
1)
#25000
0*
0)
#26000
b11 >
b1100 =
b100 D
b10000 6
00
1)
#27000
0)
#28000
b100 >
b10000 =
01
1)
